mdisky/__init__.py
mdisky/exception.py
mdisky/mdisk.py
mdisky-0.0.6.dist-info/LICENSE
mdisky-0.0.6.dist-info/METADATA
mdisky-0.0.6.dist-info/WHEEL
mdisky-0.0.6.dist-info/top_level.txt
mdisky-0.0.6.dist-info/RECORD
