Metadata-Version: 2.1
Name: mdisky
Version: 0.0.6
Summary: An Unofficial Asynchronous Python version of Mdisk API wrapper
Home-page: https://github.com/kevinnadar22/mdisky
Author: Kevin Nadar
Author-email: jesikamaraj@gmail.com
License: MIT
Keywords: python,mdisk,mdisk wrapper,mdisk convert,earn money 
Platform: UNKNOWN
Classifier: Development Status :: 1 - Planning
Classifier: Intended Audience :: Developers
Classifier: Programming Language :: Python :: 3
Classifier: Operating System :: Unix
Classifier: Operating System :: MacOS :: MacOS X
Classifier: Operating System :: Microsoft :: Windows
License-File: LICENSE
Requires-Dist: requests
